{
  "message": "پیام با موفقیت انجام شد",
  "data": [
    {
      "title": "Total Volume",
      "value": "$1,250,000",
      "icon": "💰",
      "change": "+12.5%",
      "color": "from-indigo-500 to-indigo-600"
    },
    {
      "title": "Transactions",
      "value": 1250,
      "icon": "📊",
      "change": "+8.2%",
      "color": "from-blue-500 to-blue-600"
    },
    {
      "title": "Success Rate",
      "value": "98.5%",
      "icon": "✅",
      "change": "+2.4%",
      "color": "from-emerald-500 to-emerald-600"
    },
    {
      "title": "Active Coins",
      "value": "uniqueCoins",
      "icon": "🔄",
      "change": "+0",
      "color": "from-purple-500 to-purple-600"
    }
  ]
}
